MANIFEST.in
board_manufacturing_view.xml
company_view.xml
mrp_data.xml
mrp_demo.xml
mrp_report.xml
mrp_view.xml
mrp_workflow.xml
res_config_view.xml
setup.py
./__init__.py
./__openerp__.py
./company.py
./mrp.py
./procurement.py
./product.py
./res_config.py
./stock.py
./report/__init__.py
./report/bom_structure.py
./report/mrp_production_order.py
./report/mrp_report.py
./report/order.py
./report/price.py
./report/workcenter_load.py
./tests/__init__.py
./tests/test_multicompany.py
./wizard/__init__.py
./wizard/change_production_qty.py
./wizard/mrp_price.py
./wizard/mrp_product_produce.py
./wizard/mrp_workcenter_load.py
i18n/ar.po
i18n/bg.po
i18n/bs.po
i18n/ca.po
i18n/cs.po
i18n/da.po
i18n/de.po
i18n/el.po
i18n/es.po
i18n/es_AR.po
i18n/es_BO.po
i18n/es_CL.po
i18n/es_CR.po
i18n/es_EC.po
i18n/es_MX.po
i18n/es_VE.po
i18n/et.po
i18n/fi.po
i18n/fr.po
i18n/gl.po
i18n/hi.po
i18n/hr.po
i18n/hu.po
i18n/id.po
i18n/it.po
i18n/ja.po
i18n/ko.po
i18n/lt.po
i18n/lv.po
i18n/mk.po
i18n/mn.po
i18n/mrp.pot
i18n/nb.po
i18n/nl.po
i18n/nl_BE.po
i18n/pl.po
i18n/pt.po
i18n/pt_BR.po
i18n/ro.po
i18n/ru.po
i18n/sk.po
i18n/sl.po
i18n/sq.po
i18n/sr@latin.po
i18n/sv.po
i18n/tlh.po
i18n/tr.po
i18n/uk.po
i18n/vi.po
i18n/zh_CN.po
i18n/zh_HK.po
i18n/zh_TW.po
images/bill_of_materials.jpeg
images/manufacturing-hover.png
images/manufacturing.png
images/manufacturing_analysis.jpeg
images/manufacturing_order.jpeg
images/planning_manufacturing_order.jpeg
images/production_dashboard.jpeg
images/routings.jpeg
images/work_centers.jpeg
openerp_mrp.egg-info/PKG-INFO
openerp_mrp.egg-info/SOURCES.txt
openerp_mrp.egg-info/dependency_links.txt
openerp_mrp.egg-info/requires.txt
openerp_mrp.egg-info/top_level.txt
process/procurement_process.xml
process/service_product_process.xml
process/stockable_product_process.xml
report/bom_structure.rml
report/bom_structure.sxw
report/custom_default.xsl
report/custom_rml.xsl
report/mrp_production_order_view.xml
report/mrp_report_view.xml
report/order.rml
report/order.sxw
report/price.xsl
security/ir.model.access.csv
security/mrp_security.xml
static/src/img/icon.png
test/bom_with_service_type_product.yml
test/cancel_order.yml
test/order_demo.yml
